MANIFEST.in
README.rst
setup.py
django_oneall/__init__.py
django_oneall/admin.py
django_oneall/app.py
django_oneall/auth.py
django_oneall/forms.py
django_oneall/models.py
django_oneall/tests.py
django_oneall/urls.py
django_oneall/views.py
django_oneall.egg-info/PKG-INFO
django_oneall.egg-info/SOURCES.txt
django_oneall.egg-info/dependency_links.txt
django_oneall.egg-info/requires.txt
django_oneall.egg-info/top_level.txt
django_oneall/management/__init__.py
django_oneall/management/commands/__init__.py
django_oneall/management/commands/emaillogin.py
django_oneall/management/commands/legacyimport.py
django_oneall/management/commands/setsuperuser.py
django_oneall/migrations/0001_initial.py
django_oneall/migrations/__init__.py
django_oneall/templates/oneall/header.html
django_oneall/templates/oneall/login.html
django_oneall/templates/oneall/profile.html
django_oneall/templates/oneall/share.html
django_oneall/templates/oneall/social_login.html
django_oneall/templatetags/__init__.py
django_oneall/templatetags/oneall.py